MDUS/__init__.py
MDUS/Analysis/DataShaping.py
MDUS/Analysis/Model.py
MDUS/Analysis/__init__.py
MDUS/Class/DataClass.py
MDUS/Class/DatasClass.py
MDUS/Class/MagDataClass.py
MDUS/Class/ScanDataClass.py
MDUS/Class/__init__.py
MDUS/Constant/__init__.py
MDUS/Constant/constant.py
MDUS/Convert/ConvertMag.py
MDUS/Convert/ConvertScan.py
MDUS/Convert/__init__.py
MDUS/Data/__init__.py
MDUS/Data/data.py
MDUS/Data/orbits.pkl
MDUS/Data/spkdownload.py
MDUS/Data/spice_kernel/__init__.py
MDUS/LoadData/LoadDatas.py
MDUS/LoadData/LoadFunction.py
MDUS/LoadData/LoadMag.py
MDUS/LoadData/LoadScan.py
MDUS/LoadData/__init__.py
MDUS/Plot/PlotDatas.py
MDUS/Plot/PlotMag.py
MDUS/Plot/PlotOrbit.py
MDUS/Plot/PlotScan.py
MDUS/Plot/__init__.py
MDUS/Setting/__init__.py
MDUS/Setting/setting.py
MDUS/Spice/SPICE_DOWNLOAD.txt
MDUS/Spice/SpiceSetup.py
MDUS/Spice/__init__.py
MDUS/Version/Version.py
MDUS/Version/__init__.py
mdus-0.1.6.dist-info/licenses/LICENSE
mdus-0.1.6.dist-info/METADATA
mdus-0.1.6.dist-info/WHEEL
mdus-0.1.6.dist-info/top_level.txt
mdus-0.1.6.dist-info/RECORD
