Metadata-Version: 2.4
Name: MDUS
Version: 0.1.6
Summary: MDUS: MESSENGER's Data Using System
Home-page: https://github.com/streamamz/MDUS
Author: Takuro OGAWA
Author-email: polish.stream@gmail.com
Classifier: Programming Language :: Python :: 3
Classifier: License :: OSI Approved :: MIT License
Classifier: Operating System :: OS Independent
Requires-Python: >=3.9
License-File: LICENSE
Requires-Dist: numpy
Requires-Dist: pandas
Requires-Dist: matplotlib
Requires-Dist: requests
Requires-Dist: spiceypy
Requires-Dist: KT17
Dynamic: author
Dynamic: author-email
Dynamic: classifier
Dynamic: description
Dynamic: description-content-type
Dynamic: home-page
Dynamic: license-file
Dynamic: requires-dist
Dynamic: requires-python
Dynamic: summary
